pyquest/gates.cpython-39-darwin.so
pyquest/libQuEST.dylib
pyquest/operators.cpython-39-darwin.so
pyquest/__init__.py
pyquest/quest_error.py
pyquest/initialisations.cpython-39-darwin.so
pyquest/core.cpython-39-darwin.so
pyquest/decoherence.cpython-39-darwin.so
pyquest/unitaries.cpython-39-darwin.so
pyquest-0.0.1.dist-info/RECORD
pyquest-0.0.1.dist-info/WHEEL
pyquest-0.0.1.dist-info/LICENCE.txt
pyquest-0.0.1.dist-info/top_level.txt
pyquest-0.0.1.dist-info/METADATA
