Metadata-Version: 2.1
Name: pyquest
Version: 0.0.1
Summary: A Python interface for QuEST.
Home-page: https://github.com/rrmeister/pyQuEST
Author: Richard Meister
Author-email: Richard Meister <richardm.tug@gmail.com>
License: MIT License
Project-URL: homepage, https://github.com/rrmeister/pyQuEST
Classifier: Development Status :: 2 - Pre-Alpha
Classifier: Environment :: Console
Classifier: Environment :: GPU :: NVIDIA CUDA
Classifier: Intended Audience :: Science/Research
Classifier: License :: OSI Approved :: MIT License
Classifier: Natural Language :: English
Classifier: Operating System :: MacOS :: MacOS X
Classifier: Operating System :: Microsoft :: Windows
Classifier: Operating System :: POSIX :: Linux
Classifier: Programming Language :: C++
Classifier: Programming Language :: Cython
Classifier: Programming Language :: Python :: 3 :: Only
Classifier: Topic :: Scientific/Engineering :: Physics
Requires-Python: >=3.7
License-File: ./LICENCE.txt
Requires-Dist: numpy >=1.20
